wisdomhord/__init__.py
wisdomhord/bisen.py
wisdomhord/datatypes.py
wisdomhord/wisdomhord.py
wisdomhord-0.3.1.dist-info/DESCRIPTION.rst
wisdomhord-0.3.1.dist-info/METADATA
wisdomhord-0.3.1.dist-info/RECORD
wisdomhord-0.3.1.dist-info/WHEEL
wisdomhord-0.3.1.dist-info/metadata.json
wisdomhord-0.3.1.dist-info/top_level.txt
