Metadata-Version: 2.0
Name: wisdomhord
Version: 0.3.1
Summary: Flat file db tool
Home-page: UNKNOWN
Author: Mika Naylor (Autophagy)
Author-email: mail@autophagy.io
License: UNKNOWN
Platform: UNKNOWN
Classifier: Development Status :: 3 - Alpha
Classifier: License :: OSI Approved :: MIT License
Classifier: Programming Language :: Python :: 3
Classifier: Programming Language :: Python :: 3.6
Requires-Python: >=3.6
Requires-Dist: datarum (==0.5.1)
